flask_x_openapi_schema/__init__.py
flask_x_openapi_schema/py.typed
flask_x_openapi_schema/_opt_deps/__init__.py
flask_x_openapi_schema/_opt_deps/_import_utils.py
flask_x_openapi_schema/_opt_deps/_flask_restful/__init__.py
flask_x_openapi_schema/_opt_deps/_flask_restful/placeholders.py
flask_x_openapi_schema/_opt_deps/_flask_restful/real.py
flask_x_openapi_schema/cli/__init__.py
flask_x_openapi_schema/cli/commands.py
flask_x_openapi_schema/core/__init__.py
flask_x_openapi_schema/core/cache.py
flask_x_openapi_schema/core/config.py
flask_x_openapi_schema/core/content_type_utils.py
flask_x_openapi_schema/core/decorator_base.py
flask_x_openapi_schema/core/decorator_factory.py
flask_x_openapi_schema/core/error_handlers.py
flask_x_openapi_schema/core/exceptions.py
flask_x_openapi_schema/core/logger.py
flask_x_openapi_schema/core/param_binding.py
flask_x_openapi_schema/core/request_extractors.py
flask_x_openapi_schema/core/request_processing.py
flask_x_openapi_schema/core/schema_generator.py
flask_x_openapi_schema/core/utils.py
flask_x_openapi_schema/i18n/__init__.py
flask_x_openapi_schema/i18n/i18n_model.py
flask_x_openapi_schema/i18n/i18n_string.py
flask_x_openapi_schema/models/__init__.py
flask_x_openapi_schema/models/base.py
flask_x_openapi_schema/models/content_types.py
flask_x_openapi_schema/models/file_models.py
flask_x_openapi_schema/models/responses.py
flask_x_openapi_schema/x/__init__.py
flask_x_openapi_schema/x/flask/__init__.py
flask_x_openapi_schema/x/flask/decorators.py
flask_x_openapi_schema/x/flask/utils.py
flask_x_openapi_schema/x/flask/views.py
flask_x_openapi_schema/x/flask_restful/__init__.py
flask_x_openapi_schema/x/flask_restful/decorators.py
flask_x_openapi_schema/x/flask_restful/resources.py
flask_x_openapi_schema/x/flask_restful/utils.py
flask_x_openapi_schema-0.2.0.dist-info/METADATA
flask_x_openapi_schema-0.2.0.dist-info/WHEEL
flask_x_openapi_schema-0.2.0.dist-info/licenses/LICENSE
flask_x_openapi_schema-0.2.0.dist-info/RECORD
