Metadata-Version: 2.4
Name: flask-x-openapi-schema
Version: 0.2.0
Summary: A powerful utility for automatically generating OpenAPI schemas from Flask-RESTful resources, Flask.MethodView classes, and Pydantic models.
Project-URL: Homepage, https://github.com/StrayDragon/flask-x-openapi-schema
Project-URL: Documentation, https://github.com/StrayDragon/flask-x-openapi-schema/tree/main/docs
Project-URL: Repository, https://github.com/StrayDragon/flask-x-openapi-schema.git
Project-URL: Issues, https://github.com/StrayDragon/flask-x-openapi-schema/issues
Author-email: straydragon <straydragonl@foxmail.com>
License: MIT
License-File: LICENSE
Classifier: Development Status :: 4 - Beta
Classifier: Framework :: Flask
Classifier: Intended Audience :: Developers
Classifier: License :: OSI Approved :: MIT License
Classifier: Programming Language :: Python :: 3
Classifier: Programming Language :: Python :: 3.11
Classifier: Programming Language :: Python :: 3.12
Classifier: Programming Language :: Python :: 3.13
Classifier: Topic :: Internet :: WWW/HTTP :: Dynamic Content
Classifier: Topic :: Software Development :: Libraries :: Python Modules
Requires-Python: >=3.11
Requires-Dist: flask>=2.0.0
Requires-Dist: pydantic>=2.0.0
Requires-Dist: pyyaml>=6.0
Requires-Dist: typing-extensions>=4.0.0; python_version < '3.10'
Provides-Extra: flask-restful
Requires-Dist: flask-restful>=0.3.9; extra == 'flask-restful'
